biblemategui/README.md
biblemategui/__init__.py
biblemategui/config.py
biblemategui/eliranwong.jpg
biblemategui/main.py
biblemategui/package_name.txt
biblemategui/requirements.txt
biblemategui/version.txt
biblemategui/api/api.py
biblemategui/css/original.py
biblemategui/css/tooltip.py
biblemategui/data/bible_events.py
biblemategui/data/bible_locations.py
biblemategui/data/bible_names.py
biblemategui/data/bible_timelines.py
biblemategui/data/cr_books.py
biblemategui/data/lexical_data.py
biblemategui/fonts/KoineGreek.ttf
biblemategui/fonts/sileot.ttf
biblemategui/fonts/sileotsr.ttf
biblemategui/fx/bible.py
biblemategui/fx/bible_selection_dialog.py
biblemategui/fx/cloud_index_manager.py
biblemategui/fx/location_finder.py
biblemategui/fx/original.py
biblemategui/fx/shared.py
biblemategui/fx/tooltips.py
biblemategui/js/bible.py
biblemategui/js/original.py
biblemategui/js/sync_scrolling.py
biblemategui/js/tooltip.py
biblemategui/pages/README.md
biblemategui/pages/home.py
biblemategui/pages/ai/agent.py
biblemategui/pages/ai/chat.py
biblemategui/pages/ai/partner.py
biblemategui/pages/bibles/bible_translation.py
biblemategui/pages/bibles/original_discourse.py
biblemategui/pages/bibles/original_interlinear.py
biblemategui/pages/bibles/original_linguistic.py
biblemategui/pages/bibles/original_parallel.py
biblemategui/pages/bibles/original_reader.py
biblemategui/pages/search/bible_characters.py
biblemategui/pages/search/bible_locations.py
biblemategui/pages/search/bible_maps.py
biblemategui/pages/search/bible_names.py
biblemategui/pages/search/bible_parallels.py
biblemategui/pages/search/bible_promises.py
biblemategui/pages/search/bible_relationships.py
biblemategui/pages/search/bible_topics.py
biblemategui/pages/search/bible_verses.py
biblemategui/pages/search/dictionaries.py
biblemategui/pages/search/encyclopedias.py
biblemategui/pages/search/lexicons.py
biblemategui/pages/teachings/parousia.py
biblemategui/pages/teachings/parousia_zh.py
biblemategui/pages/tools/analysis.py
biblemategui-0.2.63.dist-info/METADATA
biblemategui-0.2.63.dist-info/WHEEL
biblemategui-0.2.63.dist-info/entry_points.txt
biblemategui-0.2.63.dist-info/top_level.txt
biblemategui-0.2.63.dist-info/RECORD
