Metadata-Version: 2.1
Name: biblemategui
Version: 0.2.63
Summary: BibleMate AI - Automate Your Bible Study
Home-page: https://biblemate.ai
Author: Eliran Wong
Author-email: support@marvel.bible
License: GNU General Public License (GPL)
Project-URL: Source, https://github.com/eliranwong/biblemategui
Project-URL: Tracker, https://github.com/eliranwong/biblemategui/issues
Project-URL: Documentation, https://github.com/eliranwong/biblemategui/wiki
Project-URL: Funding, https://www.paypal.me/MarvelBible
Keywords: mcp agent biblemate ai anthropic azure chatgpt cohere deepseek genai github googleai groq llamacpp mistral ollama openai vertexai xai
Classifier: Development Status :: 5 - Production/Stable
Classifier: Intended Audience :: End Users/Desktop
Classifier: Topic :: Utilities
Classifier: Topic :: Scientific/Engineering :: Artificial Intelligence
Classifier: Topic :: Software Development :: Build Tools
Classifier: License :: OSI Approved :: GNU General Public License v3 or later (GPLv3+)
Classifier: Programming Language :: Python :: 3.10
Classifier: Programming Language :: Python :: 3.11
Classifier: Programming Language :: Python :: 3.12
Requires-Python: >=3.10, <3.13
Requires-Dist: agentmake >=1.1.90
Requires-Dist: apsw
Requires-Dist: authlib
Requires-Dist: biblemate >=0.2.49
Requires-Dist: google-api-python-client
Requires-Dist: google-auth-httplib2
Requires-Dist: google-auth-oauthlib
Requires-Dist: markdown2
Requires-Dist: nicegui >=3.2.0
Requires-Dist: pillow
Requires-Dist: qrcode
Provides-Extra: genai
Requires-Dist: google-genai >=1.46.0 ; extra == 'genai'
